xmlpatcher/__init__.py
xmlpatcher/py.typed
xmlpatcher/transformation.py
xmlpatcher/xml_document.py
xmlpatcher/patches/__init__.py
xmlpatcher/patches/add_child.py
xmlpatcher/patches/patch.py
xmlpatcher/patches/remove.py
xmlpatcher/patches/set_value.py
xmlpatcher-1.0.3.dist-info/LICENSE
xmlpatcher-1.0.3.dist-info/METADATA
xmlpatcher-1.0.3.dist-info/WHEEL
xmlpatcher-1.0.3.dist-info/top_level.txt
xmlpatcher-1.0.3.dist-info/RECORD
