Metadata-Version: 2.1
Name: xmlpatcher
Version: 1.0.3
Summary: A convenient library for patching XML files with XPath.
Author-email: Bip901 <74911767+Bip901@users.noreply.github.com>
Project-URL: Homepage, https://github.com/Bip901/xmlpatcher
Classifier: Programming Language :: Python :: 3
Classifier: License :: OSI Approved :: MIT License
Classifier: Operating System :: OS Independent
Requires-Python: >=3.7
License-File: LICENSE
Requires-Dist: lxml <5,>=4.9.3
